pyopenjtalk/__init__.py
pyopenjtalk/__main__.py
pyopenjtalk/htsengine.cpython-311-x86_64-linux-gnu.so
pyopenjtalk/htsengine.pyi
pyopenjtalk/openjtalk.cpython-311-x86_64-linux-gnu.so
pyopenjtalk/openjtalk.pyi
pyopenjtalk/py.typed
pyopenjtalk/types.py
pyopenjtalk/utils.py
pyopenjtalk/version.py
pyopenjtalk/dictionary/COPYING
pyopenjtalk/dictionary/char.bin
pyopenjtalk/dictionary/left-id.def
pyopenjtalk/dictionary/matrix.bin
pyopenjtalk/dictionary/pos-id.def
pyopenjtalk/dictionary/rewrite.def
pyopenjtalk/dictionary/right-id.def
pyopenjtalk/dictionary/sys.dic
pyopenjtalk/dictionary/unk.dic
pyopenjtalk/htsvoice/LICENSE_mei_normal.htsvoice
pyopenjtalk/htsvoice/mei_normal.htsvoice
pyopenjtalk/sbv2_e2k/_create_eng_dict.py
pyopenjtalk/sbv2_e2k/iataiji_map.py
pyopenjtalk/sbv2_e2k/katakana_map.py
pyopenjtalk/sbv2_e2k/normalizer.py
pyopenjtalk/sbv2_e2k/romkan.py
pyopenjtalk/sbv2_e2k/symbols.py
pyopenjtalk/sbv2_hougen/hougen.py
pyopenjtalk/sbv2_hougen/strenum.py
pyopenjtalk/user_dictionary/JMnedict_kanji_2gram.dic
pyopenjtalk/user_dictionary/JMnedict_kanji_3gram.dic
pyopenjtalk/user_dictionary/bccwj_01_2gram.dic
pyopenjtalk/user_dictionary/bccwj_01_3gram.dic
pyopenjtalk/user_dictionary/bccwj_01_4gram.dic
pyopenjtalk/user_dictionary/bccwj_02_2gram.dic
pyopenjtalk/user_dictionary/bccwj_02_3gram.dic
pyopenjtalk/user_dictionary/bccwj_02_4gram.dic
pyopenjtalk/user_dictionary/bccwj_03_2gram.dic
pyopenjtalk/user_dictionary/bccwj_03_3gram.dic
pyopenjtalk/user_dictionary/bccwj_03_4gram.dic
pyopenjtalk/user_dictionary/bccwj_04_2gram.dic
pyopenjtalk/user_dictionary/bccwj_04_3gram.dic
pyopenjtalk/user_dictionary/bccwj_04_4gram.dic
pyopenjtalk/user_dictionary/bccwj_05_2gram.dic
pyopenjtalk/user_dictionary/bccwj_05_3gram.dic
pyopenjtalk/user_dictionary/bccwj_05_4gram.dic
pyopenjtalk/user_dictionary/english.dic
pyopenjtalk/user_dictionary/filler-jouyou.dic
pyopenjtalk/user_dictionary/jawiki-kana-kanji-01-kanji-2gram.dic
pyopenjtalk_agpl3-4.13.7.dist-info/METADATA
pyopenjtalk_agpl3-4.13.7.dist-info/WHEEL
pyopenjtalk_agpl3-4.13.7.dist-info/top_level.txt
pyopenjtalk_agpl3-4.13.7.dist-info/RECORD
pyopenjtalk_agpl3-4.13.7.dist-info/licenses/LICENSE.txt
